acronyms/__init__.py
acronyms/acronym.py
acronyms/acronym_filter.py
acronyms/acronyms.py
acronyms/index.py
acronyms/json_codec.py
acronyms/logging.py
filter/__init__.py
filter/pandocacronyms.py
tests/__init__.py
tests/test_acronym.py
tests/test_acronym_filter.py
tests/test_acronyms.py
tests/test_index.py
tests/test_tools.py
pandoc_acronyms-0.6.202312121715.dist-info/LICENSE
pandoc_acronyms-0.6.202312121715.dist-info/METADATA
pandoc_acronyms-0.6.202312121715.dist-info/WHEEL
pandoc_acronyms-0.6.202312121715.dist-info/entry_points.txt
pandoc_acronyms-0.6.202312121715.dist-info/top_level.txt
pandoc_acronyms-0.6.202312121715.dist-info/RECORD
