Metadata-Version: 2.1
Name: pandoc-acronyms
Version: 0.6.202312121715
Summary: A Python filter to manage acronyms
Home-page: https://gitlab.com/mirkoboehm/pandoc-acronyms
Author: Mirko Boehm
Author-email: mirko@kde.org
License: UNKNOWN
Platform: UNKNOWN
Classifier: Programming Language :: Python :: 3
Classifier: License :: OSI Approved :: Apache Software License
Classifier: Operating System :: OS Independent
Classifier: Development Status :: 4 - Beta
Requires-Python: >=3.6
License-File: LICENSE
Requires-Dist: Click
Requires-Dist: panflute
Requires-Dist: pyyaml
